{
  "class": 3,
  "subject": "EVS",
  "subjectDisplay": "Our Wondrous World",
  "bookCode": "ceev1",
  "subSubject": null,
  "chapterNum": 11,
  "title": "Making Things",
  "language": "english",
  "sections": [
    {
      "heading": "Making Things",
      "content": "135135\nChapter\nMaking Things\nYou must have seen or used a pot for storing water.\nYou have also seen a gullak piggy bank), birdbath,\ncup (kulhad) and so many such things at home and\naround you.\nHave you ever wondered?\n• What are these things made of?\n• Who has made them and how?\nReprint 2026-27\nOur Wondrous World | Class 3\nA potter’s family\nIn a town by the seaside, Mini watched her\nAppooppan (grandfather) making a pot. He would\ntake the clay and make it wet. He would add enough\nwater to make the consistency he needed. Then\nhe pounded it well. He made sure that the clay\nwas neither too watery nor too dry. He kneaded\nthe clay like dough. Finally, he put the clay\non a stone wheel and shaped it by\nspinning it.\nWhen the pots were\ndried, Ammu (mother)\nmoved them into a very\nhot fire burning inside\na big oven. The potter’s\noven is called a ‘kiln’. This\nfire would bake the pot.\nThen the pot was ready for\nReprint 2026-27\nMaking Things\nuse. Appooppan, Ammu and other family members\nmade some patterns on some of the pots to make\nthe pots look even more beautiful.\n• What are pots used for?\n• What other kinds of things do potters make?\n• Why is the pot baked in a kiln?\n• Visit a potter in your neighbourhood with your\nparents or elders in the family.\n• Observe how the potter works on the stone wheel or\nthe potter’s wheel.\n• Have you wondered how clay takes a beautiful\nshape on a spinning wheel?\n• Which of the products made by a potter do you use\nat home?\n• Draw some of the products that you have seen at\nthe potter’s place in the box given below.\nReprint 2026-27\nOur Wondrous World | Class 3\nMini was too young\nto use the potter’s\nwheel. But she helped\nher grandfather make\npatterns on the pots\nand colour them. Her\nfavourite clay item was\nher piggy bank. She\nloved creating beautiful\npatterns on it. She then\nused it to save money.\nIn what ways do you help your parents and\ngrandparents?\nMake your own clay\n(Do this activity with the help of elders)\n• Collect soil from wet or muddy places.\n• Remove any big pebbles or stones, sand, leaves or\nparts of plants from it using a net or sieve.\n• Put this soil in a flat vessel filled with water.\n• After a few days, throw away the water that stays on\ntop.\n• Now make dough that you can shape into a ball.\nMake any two\nthings you like with\nthe clay that you have\nmade. Put it out in the\nsun to dry.\nReprint 2026-27\nMaking Things\nArrange the images in the correct order by numbering\nthem from 1 to 6.\nPatterns in Nature\nPatterns can be found\neverywhere in nature, be it\nspots on a leopard or stripes\non a squirrel. Many artists who\npaint on pots get ideas for their\nart from nature. Patterns can\nbe formed using shapes and\ncolours from nature.\nYou must have seen\npatterns on plants and animals\naround you. For example, if\nyou observe the leaves on the\nbranches of a tree like the\nneem, you will find a pattern.\nSimilarly, patterns can also\nbe seen on some animals like\nthe zebra, peacock, cat, tiger,\nbutterfly, fish, etc.\nReprint 2026-27\nOur Wondrous World | Class 3\nThe following are some patterns with repeating shapes and\nlines.\nLook around for patterns on plants.\nDraw any pattern of a leaf in the given\nbox. Give an example of your own.\nLook around for patterns on animals.\nDraw an animal which has patterns\non its body.\nLook around for patterns on things.\nDraw a pattern in the box.\nReprint 2026-27\nMaking Things\nDecorate the given objects with patterns.\npatterns in Indian pottery\nThese are some beautiful forms of pottery from\ndifferent parts of India.\nTick the ones that have patterns on them.\nReprint 2026-27\nOur Wondrous World | Class 3\nBy now, you are familiar with pots made of clay. Let\nus read about bricks.\nBrick by Brick\n• Where have you seen bricks?\n• Have you ever seen how bricks are made?\nBricks are also made of mud just like the pots\nprepared by Appooppan.\nYou must have seen idli, cake, dhokla or kulfi\nmoulds. Similarly, bricks are also prepared in\n‘moulds’ to give them their shape. A brick becomes\nhard after it is baked in the kiln. Bricks are used for\nconstruction of buildings such as houses, schools,\nand hospitals.\nReprint 2026-27\nMaking Things\nRohan and his father live in Jaipur. Rohan loves\nto see houses being built. He is amazed at how his\nfather and his co-workers can construct such tall\nand beautiful buildings.\nRohan’s favourite pastime is watching brick\nwalls getting built. He had been watching one\nparticular wall being built.\nWith each passing day, Rohan could see that\nbrick by brick the wall was completed. After\na few months, Rohan saw that it had\nbecome a big building.\nReprint 2026-27\nOur Wondrous World | Class 3\n• Are all houses made of bricks?\n• What do you think are other materials used to build\nhouses?\nIn some warm areas of our country, people make\ntraditional mud houses to keep them cool inside.\nPeople use natural materials like grass and wood.\nInstead of cement, many people use cow dung to\nmake smooth walls and floors. Cow dung keeps the\nheat out and stops insects from entering the house.\n1. Why do you think mud houses are better for the\nenvironment?\n_____________________________________________________________\n_____________________________________________________________\n2. Look around at the houses in your neighbourhood.\nWhat are the houses made of?\n_____________________________________________________________\n_____________________________________________________________\nReprint 2026-27\nMaking Things\nLook at the pictures below. Guess the name of each type of\nhouse. Fill it in the given table below.\nWhat are these\nhouses made of?\nWhat is this type\nof a house called?\nPictures of houses\nReprint 2026-27\nOur Wondrous World | Class 3\nMake a Wall\nMake some bricks using\na matchbox mould, small\npaper boxes, clay or atta\n(dough). Stack them in\nthese two arrangements\nshown in the drawing.\n• Which one is sturdier ?\n• Which one falls more easily when pushed?\nSafety first\nRohan’s father follows all the important safety\nrules while working. For example, he always wears\na helmet with a strap, a safety vest and sturdy\nfootwear.\n• Are there any safety rules at home?\n• Do you have any safety rules at school?\nReprint 2026-27\nMaking Things\nLet us reflect\nA. Write\n1. What is the process of pot making?\n2. How do artists get ideas for their arts?\n3. What is a kiln?\n4. What are houses made of?\n5. You may also try to find videos on YouTube that\nshow the process of things being made. Write down\nthe steps in as much detail as possible.\nB. Draw and colour any three different kinds of houses.\nC. Discuss\n1. Why do we have different kinds of houses?\n2. Why do people wear helmets at construction sites?\n3. What would happen if there were no patterns\nin nature?\nD. Interview\n1. Interview someone who makes crafts or toys in your\nlocality. Share the information in the class.\n2. Find out how some commonly used objects like\npencils, erasers, pens and notebooks are made. Ask\nyour elders.\nReprint 2026-27\nOur Wondrous World | Class 3\nHave you seen any statues in your town or city?\nDo you know if these statues are also made of the same\nclay that is used to make pots and bricks?\nReprint 2026-27",
      "type": "procedure"
    }
  ],
  "learningObjectives": [
    "Understand the key concepts of Making Things",
    "Identify and explain the main ideas covered in this chapter",
    "Apply knowledge from this chapter to real-world situations",
    "Recall important terms and definitions from Making Things"
  ],
  "wordCount": 1285,
  "pdfUrl": "https://ncert.nic.in/textbook/pdf/ceev111.pdf",
  "extractedAt": "2026-05-20T22:22:21.973Z"
}