{
  "class": 7,
  "subject": "Social Science",
  "subjectDisplay": "Ganita Prakash II",
  "bookCode": "gegp2",
  "subSubject": "Geography",
  "chapterNum": 1,
  "title": "Geometric",
  "language": "english",
  "sections": [
    {
      "heading": "Geometric",
      "content": "GEOMETRIC\nTWINS\n1.1 Geometric Twins\nThe symbol on this signboard needs to be recreated on another board.\nHow do we do it?\nOne way is to trace the outline of this symbol on tracing paper to\nreconstruct the figure. But this is difficult for big symbols. What else can\nwe do?\nCan we take some measurements that would allow us to exactly recreate\nthis figure? If yes, what measurements should we take?\nLet us name the corner points of this symbol as shown.\nA C\nB\nAre the arm lengths AB and BC sufficient to exactly recreate this figure?\nGanita Prakash | Grade 7 | Part-II\nSuppose these lengths are AB = 4 cm, BC = 8 cm. We observe that\nseveral such symbols can be constructed with the same lengths.\nA\nB\nC\nA\nB\nC\nA\nB\nC\nA\nB\nC\nTo get the exact replica, would it help to take any other measurement?\nThe measure of ∠ABC, along with the two arm lengths AB and BC, fix\nthe shape and size of this figure.\nCan you draw the symbol if it is known that AB = 4 cm, BC = 8 cm, and\n∠ABC = 80°?\nThese three measurements can help us create an exact replica of the\nsymbol on the signboard. Figures that are exact copies of each other\nor have the same shape and size are said to be congruent. Congruent\nfigures can be superimposed exactly, one over the other.\nTwo congruent figures are shown below. You could use a tracing\npaper to trace the first figure and superimpose it on the second one. You\nwill find that they fit exactly, one over the other.\nNote that while checking for congruence, a figure can be rotated or\nflipped before superimposing it on the other figure. So, the following\npairs of figures are also congruent to each other.\nGeometric Twins\nLet us get back to the symbol we saw on the signboard. Suppose there\nare two such symbols that look identical and we need to confirm that they\nare indeed congruent. Can we use their measurements to verify this?\nIf it is known that both symbols have the same arm lengths, can it be\nconcluded that the two symbols are congruent?\nWe have seen that there can exist several such non-congruent figures\nwith different angles between the given arm lengths. Fixing the angle\ndetermines the shape and size of the figure.\nThus, if both symbols have the same arm lengths and angle, we can be\nsure that the figures are congruent.\nFigure it Out\n1. Check if the two figures are congruent.\n2. Circle the pairs that appear congruent.\n3. What measurements would you take to create a figure congruent to\na given:\n(a) Circle (b) Rectangle\nGanita Prakash | Grade 7 | Part-II\n\u0007Using\u0007this,\u0007state\u0007how\u0007would\u0007you\u0007check\u0007if\u0007two —\n(a) Circles are congruent?\n(b) Rectangles are congruent?\n4. How would we check if two figures like the one below are congruent?\nUse this to identify whether each of the following pairs are congruent.",
      "type": "text"
    },
    {
      "heading": "1.2 Congruence of Triangles",
      "content": "Meera and Rabia have been asked to make a cardboard cutout identical\nto a triangular frame they have in school. They see that the frame is too\nbig to be traced on a paper and replicated.\nGeometric Twins\nWhat do you think they can do?\nMeasuring the Sidelengths\nCan certain measurements of the triangle be used for this? Using a\nmeasuring tape, the girls measure the sides of the triangle to be 40 cm,\n60 cm, and 80 cm.\nThen, Rabia takes out her protractor to measure the angles. She is\nstopped by Meera.\nMeera: The angles of the triangle are not required! With the side\nlengths we have measured, we can create a triangle congruent to this\none.\nDo you agree with Meera?\nInstead of the lengths being 40 cm, 60 cm, and 80 cm, suppose the\nsidelengths had been 4 cm, 6 cm, 8 cm (this triangle can fit on our page).\nIs this information sufficient to replicate the triangle with the same size\nand shape? If yes, can you do so?\nRabia: If I were to construct this triangle, I would first draw a line\nsegment having one of the given lengths, say 6 cm, and then draw circles\nfrom each of its end points with radii 4 cm and 8 cm. But the circles\nwould intersect at two points, forming two triangles:\n∆ABE and ∆ABF\nBA \nAB = 6 cm\nE\nF\nRabia: Do these two triangles have the same shape and size? If not,\nthen we will not be sure which of these would actually be congruent to\nthe original triangle we are trying to replicate.\nGanita Prakash | Grade 7 | Part-II\nExamine\u0007whether\u0007∆ABE\u0007and\u0007∆ABF\u0007are\u0007congruent.\nFor\u0007this,\u0007you\u0007could\u0007use\u0007one\u0007or\u0007more\u0007of\u0007the\u0007following\u0007methods —\u0007tracing\u0007\nand comparing, taking a cutout and superimposing, or observing that AB\nacts as a line of symmetry due to the ‘sameness’ of the act of construction\nabove and below this line.\nWe\u0007 see\u0007 that\u0007 ∆ABE\u0007 and\u0007 ∆ABF\u0007 are\u0007 congruent.\u0007 From\u0007 this\u0007 general\u0007\nconstruction, we can see that all triangles with the same sidelengths are\ncongruent. Hence, Meera was right when she said that the sidelengths\nare sufficient to construct a congruent triangle.\nThus, we have the following result:\nIf two triangles have the same sidelengths, then they are congruent.\nWe call this the SSS (Side Side Side) condition for congruence.\nConventions to Express Congruence\nThe two triangles given below are congruent. How can these two triangles\nbe\u0007superimposed?\u0007Which\u0007vertices\u0007of\u0007∆XYZ\u0007and\u0007∆ABC\u0007should\u0007we\u0007overlap?\nThis has to be done so that the equal sides overlap. Figure out how.\nC\nA B Y\nX\nZ\nOverlapping\u0007Vertex\u0007A\u0007over\u0007Vertex\u0007X,\u0007Vertex\u0007B\u0007over\u0007Vertex\u0007Y\u0007and\u0007Vertex\u0007\nC\u0007over\u0007Vertex\u0007Z\u0007will\u0007ensure\u0007that\u0007equal\u0007sides\u0007overlap,\u0007making\u0007the\u0007triangles\u0007\nfit exactly over each other.\nAre\u0007there\u0007other\u0007ways\u0007of\u0007overlapping\u0007the\u0007vertices\u0007so\u0007that\u0007the\u0007triangles\u0007fit\u0007\nexactly over each other?\nThe fact that these triangles are congruent shows that their respective\nangles are equal:\n∠A = ∠X,\u0007∠B = ∠Y and ∠C = ∠Z\nThus, when two triangles are congruent, there are corresponding\nvertices, sides and angles which fit exactly over each other when the\ntriangles are made to overlap. In this case, they are\n(a)\u0007 Corresponding\u0007Vertices:\u0007A\u0007and\u0007X,\u0007B\u0007and\u0007Y,\u0007C\u0007and\u0007Z\nGeometric Twins\n(b)\u0007Corresponding\u0007Sides:\u0007AB\u0007and\u0007XY,\u0007BC\u0007and\u0007YZ,\u0007AC\u0007and\u0007XZ\n(c) Corresponding Angles: ∠A and ∠X,\u0007∠B and ∠Y, ∠C and ∠Z\nTo capture this relation that exists when two triangles are congruent,\ntheir congruence is written as follows:\n∆ABC\u0007≅\u0007∆XYZ\n∆ABC ≅\u0007\u0007\u0007∆XYZ\nc\no\nr\nr\ne\ns\np\no\nn\nd\ns\nt\no\nc\no\nr\nr\ne\ns p o n d s\nt\no\nc\no\nr\nr\ne\ns\np\no\nn\nd\ns\nto\nBy writing this, we mean that:\n• the\u0007first\u0007vertex\u0007in\u0007the\u0007name\u0007of\u0007∆ABC\u0007corresponds\u0007to\u0007the\u0007first\u0007vertex\u0007\nin\u0007the\u0007name\u0007of\u0007∆XYZ,\n• the\u0007second\u0007vertex\u0007in\u0007the\u0007name\u0007of\u0007∆ABC\u0007corresponds\u0007to\u0007the\u0007second\u0007\nvertex\u0007in\u0007the\u0007name\u0007of\u0007∆XYZ,\u0007and\n• similarly\u0007with\u0007the\u0007third\u0007vertices\u0007in\u0007the\u0007names\u0007of\u0007∆ABC\u0007and\u0007∆XYZ.\nBy this convention, it is incorrect to write for these two triangles that\n∆ACB\u0007≅\u0007∆XYZ.\nHowever, another correct way of saying it is\n∆ACB\u0007≅\u0007∆XZY.\nCan you identify a pair of congruent triangles below? Why are they\ncongruent?\nA B\nD C\nFig.1.1\nConsider\u0007∆ABD\u0007and\u0007∆CDB.\u0007Since\u0007ABCD\u0007is\u0007a\u0007rectangle,\u0007we\u0007have\nAB = CD\nAD = CB\nIf\u0007the\u0007remaining\u0007sides\u0007of\u0007∆ABD\u0007and\u0007∆CDB\u0007have\u0007the\u0007same\u0007length\u0007then\u0007\nthe SSS condition is satisfied, confirming the congruence of the two\ntriangles. Is this the case?\nGanita Prakash | Grade 7 | Part-II\nThe remaining side is a common side BD, so the SSS condition holds.\nHence, the triangles are congruent.\nWe know the corresponding sides of the two triangles. We have to\nidentify the corresponding vertices. Can they be the following?\n∆ABD ∆CDB\nA C\nB B\nD D\nVerify this by superimposing paper cutouts of the triangles obtained\nfrom the rectangle ABCD (Fig. 1.1).\nWe\u0007 see\u0007 that\u0007 this\u0007 correspondence\u0007 lays\u0007 the\u0007 side\u0007 AB\u0007 of\u0007 ∆ABD\u0007 over\u0007 the\u0007\nside\u0007 CB\u0007 of\u0007 ∆CDB.\u0007 But\u0007 these\u0007 sides\u0007 need\u0007 not\u0007 be\u0007 equal,\u0007 and\u0007 hence,\u0007 this\u0007\nsuperimposition will not establish congruence.\nIdentify the correct correspondence of vertices and express the\ncongruence between the two triangles.\nFigure it Out\n1. Suppose\u0007∆HEN\u0007is\u0007congruent\u0007to\u0007∆BIG.\u0007List\u0007all\u0007the\u0007other\u0007correct\u0007ways\u0007\nof expressing this congruence.\n2. Determine whether the triangles are congruent. If yes, express the\ncongruence.\nR\nE D\n3.5 cm\n5 cm\n6 cm\nJ\nM\nA\n3.5 cm\n5 cm\n6 cm\nGeometric Twins\n3. In the figure below, AB = AD, CB = CD.\nCan you identify any pair of congruent triangles? If yes, explain why\nthey are congruent.\nDoes AC divide ∠BAD and ∠BCD into two equal parts? Give reasons.\nA\nB\nC\nD\n4. In the figure below, are ΔDFE and ΔGED congruent to each other? It\nis given that DF = DG and FE = GE.\nF G\nD\nE\nMeasuring the Angles\nInstead of measuring the three sidelengths of the triangular frame, if\nMeera and Rabia measure the three angles, can they recreate the triangle\nexactly?\nSuppose the angles are 30°, 70°, and 80°. Can we create an exact copy of\nthe frame with this?\nAs we see, we can draw many triangles with these measurements that\nare not congruent.\nGanita Prakash | Grade 7 | Part-II\n80°\n30°\nB C\nA\n70°\n80°\n30°\nA\nCB \n70° 30°\n80°\nA\nCB \n70°\nThese triangles are seen to have the same shape, but not the same\nsize. Hence, two triangles that have the same set of angles need not\nbe congruent.\nMeasuring Two Sides and the Included Angle\n∆ABC\u0007and\u0007∆XYZ\u0007are\u0007two\u0007triangles\u0007such\u0007that\nAB\u0007=\u0007XY\u0007=\u00076\u0007cm,\u0007AC\u0007=\u0007XZ\u0007=\u00075\u0007cm,\u0007and\u0007∠A = ∠X\u0007=\u000730°\nAre they congruent?\nTo check this, we need to see if there can exist non-congruent triangles\nwith the given measurements.\nThese measurements correspond to the case of two sides and the\nincluded angle. We have seen how to construct a triangle given these\nmeasurements.\nConstruct a triangle having the above measurements.\nCompare it with the triangles constructed by your classmates. Are\nthe\u0007 triangles\u0007 all\u0007 congruent?\u0007 Explain\u0007 why\u0007 all\u0007 such\u0007 triangles\u0007 with\u0007 these\u0007\nmeasurements are congruent.\nThus, when two sides and the included angle of two triangles are\nequal, the two triangles are congruent.\nThis is referred to as the SAS (Side Angle Side) condition for\ncongruence.\nMeasuring Two Sides and a Non-included Angle\nWhat if two sides and a non-included angle are equal?\n∆ABC\u0007and\u0007∆XYZ\u0007are\u0007two\u0007triangles\u0007such\u0007that\nAB\u0007=\u0007XY\u0007=\u00076\u0007cm,\u0007AC\u0007=\u0007XZ\u0007=\u00074\u0007cm,\u0007and\u0007∠B = ∠Y = 30°\nAre they congruent?\nCan there exist non-congruent triangles having these measurements?\nConstruct\u0007and\u0007find\u0007out.\nGeometric Twins\nLooking at a rough diagram helps in planning the construction.\nR\nP Q\n30°\n6 cm\n4 cm\nHow does one construct a triangle having these measurements?\nStep 1: Draw the base PQ of length 6 cm.\nStep 2: Draw a line l from P that makes an angle of 30° with PQ.\nP Q\nl\n6 cm\n30°\nStep 3:\u0007\u0007Draw\u0007 a\u0007 sufficiently\u0007 long\u0007 arc\u0007 from\u0007 Q\u0007 of\u0007 radius\u0007 4\u0007 cm\u0007 cutting\u0007 the\u0007\nline l.\nP Q\n6 cm\n30°\nR\nS\nHow\u0007do\u0007we\u0007find\u0007the\u0007required\u0007triangle\u0007from\u0007this\u0007figure?\nA point of intersection of the arc and the line l gives the third point of\nthe required triangle. But we see that the arc intersects the line l at two\ndifferent points R and S.\nBoth\u0007∆PQR\u0007and\u0007∆PQS\u0007satisfy\u0007the\u0007given\u0007measurements.\u0007\nl\nGanita Prakash | Grade 7 | Part-II\nR\nP Q\n30°\n6 cm\n4 cm\ns\nP Q\n30°\n6 cm\n4 cm\nHence, we can draw two non-congruent triangles with the given\nmeasurements.\nThis is called the SSA (Side Side Angle) condition. We have seen that\nSSA condition does not guarantee congruence.\nWe have examined cases using two sides and an angle for determining\ncongruence. Can we use two angles and a side?\nLet us first take the case of two angles and the included side.\nTwo Angles and the Included Side\nΔABC and ΔXYZ are two triangles with,\nBC = YZ = 5 cm, ∠B = ∠Y = 50° and ∠C = ∠Z = 30°.\nAre they congruent?\nCan there exist non-congruent triangles having these measurements?\nConstruct and find out.\nWe have seen how to construct a triangle when we are given two\nangles and the included side.\nThis construction should make it clear that all the triangles\nhaving these measurements must be congruent to each other. Hence,\nΔABC ≅ ΔXYZ.\nThis condition is referred to as the ASA (Angle Side Angle) condition\nfor congruence.\nIn the figure, Point O is the midpoint of AD and BC. What can one say\nabout the lengths AB and CD?\nA C\nD\nB\nO\nGeometric Twins\nWe have,\nAO = OD (as O is the midpoint of AD)\nBO = OC (as O is the midpoint of BC).\nAre there any other equal sides or angles?\nWe also have,\n∠AOB = ∠DOC, as they are vertically opposite angles.\nWe see that the SAS condition (two sides and the included angle) is\nsatisfied, and so we can conclude that the triangles are congruent.\nWhat are the Corresponding Vertices?\nAs we need AO and OD to overlap, and BO and CO to overlap for the\ntriangles to exactly fit over each other, the corresponding vertices\nin ΔAOB and ΔDOC are A and D, O and O (vertex common to both the\ntriangles), and B and C. Thus,\nΔAOB ≅ ΔDOC.\nAB and DC are corresponding sides as they overlap when the triangles\nare superimposed. Thus, their lengths are equal.\nFigure it Out\n1. Identify whether the triangles below are congruent. What conditions\ndid you use to establish their congruence? Express the congruence.\nA\n7 cm\nB\n5 cm C\n47°\nX\nY\nZ\n7 cm\n5 cm\n47°\n2. Given that CD and AB are parallel, and AB = CD, what are the other\nequal parts in this figure? (Hint: When the lines are parallel, the\nalternate angles are equal. Are the two resulting triangles congruent?\nIf so, express the congruence.)\nGanita Prakash | Grade 7 | Part-II\nD\nA\nB\nC\nO\n3. Given that ∠ABC = ∠DBC and ∠ACB = ∠DCB, show that\n∠BAC = ∠BDC. Are the two triangles congruent?\nA\nD\nCB\n4. Identify the equal parts in the following figure, given that ∠ABD =\n∠DCA and ∠ACB = ∠DBC.\nA\nB C\nD\nMeasuring Two Angles and a Non-Included Side\nThe following triangles ΔABC and ΔXYZ are such that ∠A = ∠X = 35°,\n∠C = ∠Z = 75°, and BC = YZ = 4 cm. Are the triangles congruent? Give\na reason.\nGeometric Twins\nA\nB C\n4 cm\n75°\n35°\nX\nY Z\n4 cm\n75°\n35°\nFig.1.2\nHow do we proceed with this problem? Here is a method.\nWhat are the measures of ∠B and ∠Y?\nWe know that the sum of the angles of a triangle is 180°.\nSo ∠B + 35° + 75° = 180°,\nor ∠B + 110° = 180°\nThus, ∠B = 70°.\nSimilarly, ∠Y is also 70°.\nThus, we have ∠B = ∠Y.\nDoes\u0007this\u0007help\u0007in\u0007showing\u0007that\u0007∆ABC\u0007and\u0007∆XYZ\u0007are\u0007congruent?\nA\nB C\n4 cm\n75°70°\n35°\n70°\nX\nY Z\n4 cm\n75°\n35°\nThese two triangles now satisfy the ASA condition with\n∠B = ∠Y\nBC\u0007=\u0007YZ\u0007\n∠C = ∠Z\nSo,\u0007∆ABC\u0007≅ ∆XYZ.\nGanita Prakash | Grade 7 | Part-II\nIn Fig. 1.2, the equalities are between two angles and the\nnon-included side of the two triangles. This condition is referred to as\nthe AAS (Angle Angle Side) condition.\nAs we have seen, the AAS condition guarantees congruence.\nWe have seen that the SSA condition doesn’t always guarantee\ncongruence. However, there are some special cases when SSA does\nguarantee congruence. Here is one such important case.\nMeasuring Two Sides in a Right Triangle\n∆ABC\u0007 and\u0007 ∆XYZ\u0007 are\u0007 right-angled\u0007 triangles\u0007 such\u0007 that\u0007 BC\u0007 =\u0007 YZ\u0007 =\u0007 4\u0007 cm,\u0007\n∠B = ∠Y\u0007=\u000790°\u0007and\u0007AC\u0007=\u0007XZ=5cm.\u0007Are\u0007they\u0007congruent?\nCan there exist non-congruent triangles having these measurements?\nConstruct and find out.\nLooking at the rough diagram helps in planning the construction.\nP\nQ R\n4 cm\n5 cm\nStep 1: Draw the base QR of length 4 cm.\nStep 2: Draw a line l perpendicular to QR from Q.\nStep 3: From R, cut an arc on line l of radius 5 cm.\nStep 4: Let P be the point at which the arc intersects the line l. Join PR.\nP\nQ R4 cm\n∆PQR\u0007is\u0007the\u0007required\u0007triangle.\nGeometric Twins\nConsider the downward extension of line l below QR. Would the arc\nfrom R meet this line downwards as well (as in the case of triangle\nconstruction when the sidelengths are given)? If so, would this lead to a\ntriangle\u0007whose\u0007size\u0007and\u0007shape\u0007are\u0007different\u0007from\u0007∆PQR,\u0007and\u0007yet\u0007has\u0007the\u0007\ngiven measurements?\nIt can be seen that the other triangle we get below is also congruent to\n∆PQR.\u0007Why?\u0007Therefore,\u0007all\u0007triangles\u0007having\u0007these\u0007measurements\u0007will\u0007be\u0007\ncongruent to each other.\nThus,\u0007we\u0007conclude\u0007that\u0007∆ABC\u0007≅ ∆XYZ.\nIn the case that we have considered, the parts that are equal to their\ncorresponding parts in another triangle are\n(a) the right angle\n(b) two other sides, one of which is opposite to the right angle. This\nside is called the hypotenuse.\nThis is called the RHS (Right Hypotenuse Side) condition, and is one\nmore condition for congruence.\nConditions that are sufficient to guarantee congruence\nFrom the discussions so far, we can see that two triangles are congruent\nif any of the following conditions are satisfied:\n(a) SSS condition (b) SAS condition\n(c) ASA condition (d) AAS condition\n(e) RHS condition",
      "type": "procedure"
    },
    {
      "heading": "1.3 Angles of Isosceles and Equilateral Triangles",
      "content": "Congruence is a very powerful tool for studying properties of geometric\nfigures.\u0007 Let\u0007 us\u0007 use\u0007 it\u0007 to\u0007 discover\u0007 an\u0007 important\u0007 property\u0007 of\u0007 isosceles\u0007\ntriangles.\n∆ABC\u0007is\u0007isosceles\u0007with\u0007AB\u0007=\u0007AC,\u0007and\u0007∠A = 80. What can we say about ∠B\nand ∠C?\n80°\nA\nB C\nConstruct the altitude from A to BC.\nGanita Prakash | Grade 7 | Part-II\nWe have,\nAB = AC (given)\n∠ADB = ∠ADC = 90° (from construction)\nAD\u0007is\u0007a\u0007common\u0007side\u0007of\u0007the\u0007two\u0007triangles\u0007∆ADB\u0007and\u0007∆ADC.\nA\nD\nB C\nThus,\u0007the\u0007triangles\u0007satisfy\u0007the\u0007RHS\u0007condition.\u0007Hence,\u0007∆ADB\u0007≅ ∆ADC.\nThis shows that ∠B = ∠C, as they are corresponding parts of congruent\ntriangles.\nThus, the angles opposite to equal sides are equal.\nCan you use this fact to find ∠B and ∠C?\nAngles in an Equilateral Triangle\nEquilateral\u0007triangles\u0007are\u0007those\u0007in\u0007which\u0007all\u0007the\u0007sides\u0007have\u0007equal\u0007lengths.\u0007\nWhat can we say about their angles?\nWe can use the recently discovered fact that angles opposite to equal\nsides are equal.\nA\nB C\nThe sides AB and AC are equal. So ∠B = ∠C.\nA\nB C\nGeometric Twins\nSimilarly, the sides AB and BC are equal. So ∠A = ∠C.\nSo, all the three angles of an equilateral triangle are equal, just like\ntheir sides.\nWhat could be their measures?\nAs the three angles should add up to 180°, we have\n3 × angle in an equilateral triangle = 180°.\nSo each angle is 60°.\nVerify this by construction.\nThus, just using the notion of congruence, we have deduced that the\nangles of an equilateral triangle are all 60°.\nCongruent Triangles in Real Life: Congruent triangles can be seen\nin various constructions and designs from ancient to modern times.\nHere are a few examples.\nWorld-famous Louvre Museum\nin Paris\nWorld-famous Egyptian Pyramid of Giza\nRangoli designDome design\nGanita Prakash | Grade 7 | Part-II\nRabindra Setu or Howrah Bridge\nDescribe the congruent triangles you see in each picture.\nFigure it Out\n1. ∆AIR\u0007≅ ∆FLY.\u0007Identify\u0007the\u0007corresponding\u0007vertices,\u0007sides\u0007and\u0007angles.\n2. Each\u0007 of\u0007 the\u0007 following\u0007 cases\u0007 contains\u0007 certain\u0007 measurements\u0007 taken\u0007\nfrom two triangles. Identify the pairs in which the triangles are\ncongruent\u0007 to\u0007 each\u0007 other,\u0007 with\u0007 reason.\u0007 Express\u0007 the\u0007 congruence\u0007\nwhenever they are congruent.\n(a)\u0007 AB\u0007 =\u0007DE\u0007 (b)\u0007 AB\u0007 =\u0007 EF\n\u0007 BC\u0007 =\u0007EF\u0007 \u0007 ∠A = ∠E\n\u0007 CA\u0007 =\u0007DF\u0007 \u0007 AC\u0007 =\u0007 ED\n(c) AB = DF ((d) ∠A = ∠D\n∠B = ∠D = 90° ∠B = ∠E\n\u0007 AC\u0007 =\u0007FE\u0007 \u0007 AC\u0007 =\u0007 DF\n(e) AB = DF\n∠B = ∠F\n\u0007 AC\u0007 =\u0007DE\n3. It is given that OB = OC, and OA = OD. Show that AB is parallel to CD.\n[Hint: AD is a transversal for these two lines. Are there any equal\nalternate angles?]\nD\nB\nA \nC\nO\nGeometric Twins\n4. ABCD\u0007is\u0007a\u0007square.\u0007Show\u0007that\u0007∆ABC\u0007≅ ∆ADC.\u0007Is\u0007∆ABC\u0007also\u0007congruent\u0007\nto\u0007∆CDA?\nA\nD\nB\nC\nGive\u0007 more\u0007 examples\u0007 of\u0007 two\u0007 triangles\u0007 where\u0007 one\u0007 triangle\u0007 is\u0007\ncongruent\u0007to\u0007the\u0007other\u0007in\u0007two\u0007different\u0007ways,\u0007as\u0007in\u0007the\u0007case\u0007above.\u0007\nCan you give an example of two triangles where one is congruent to\nthe\u0007other\u0007in\u0007six\u0007different\u0007ways?\n5. Find ∠B and ∠C, if A is the centre of the circle.\n120°\nA\nCB\n6. Find the missing angles. As per the convention that we have been\nfollowing, all line segments marked with a single ‘|’ are equal to each\nother and those marked with a double ‘|’ are equal to each other, etc.\n34°\n68°\n98°\n44°\n46°\n90°\n56°\n30°\n44°\n34°\n34°\n56°\nK\nR\nA\nC\nU\nL\nV\nB\nF\nD\nGanita Prakash | Grade 7 | Part-II\n• Figures that have the same shape and size are said to be congruent.\nThese figures can be superimposed so that one fits exactly over the other.\n• While verifying congruence, a figure can be rotated or flipped to make\nit fit exactly over the other figure via superimposition.\n• When two triangles have the same sidelengths, we say that the SSS\n(Side Side Side) condition is satisfied. The SSS condition guarantees\ncongruence.\n• When two sides and the included angle of one triangle are equal to the\ntwo sides and the included angle of another triangle, we say that the\nSAS (Side Angle Side) condition is satisfied. The SAS condition also\nguarantees congruence.\n• When two angles and the included side of one triangle are equal to the\ntwo angles and the included angle of another triangle, we say that the ASA\n(Angle Side Angle) condition is satisfied. The ASA condition guarantees\ncongruence. Congruence holds even if the side is not included between\nthe angles AAS (Angle Angle Side) condition.\n• In a right-angled triangle, the side opposite to the right angle is called\nthe hypotenuse.\n• When a side and a hypotenuse of a right-angled triangle are equal to a\nside and the hypotenuse of another right-angled triangle, we say that the\nRHS (Right Hypotenuse Side) condition is satisfied. The RHS condition\nalso guarantees congruence.\n• Two triangles need not be congruent if two sides and a non-included\nangle are equal.\n• In a triangle, angles opposite to equal sides are equal.\n• The angles in an equilateral triangle are all 60°.",
      "type": "text"
    },
    {
      "heading": "SUMMARY",
      "content": "Expression Engineer!\nDraw lines and split the region consisting of white squares into 6\nsmaller congruent regions.",
      "type": "text"
    }
  ],
  "learningObjectives": [
    "Understand the key concepts of Geometric",
    "Identify and explain the main ideas covered in this chapter",
    "Apply knowledge from this chapter to real-world situations",
    "Recall important terms and definitions from Geometric"
  ],
  "wordCount": 3593,
  "pdfUrl": "https://ncert.nic.in/textbook/pdf/gegp201.pdf",
  "extractedAt": "2026-05-20T22:25:10.237Z"
}