{
  "class": 2,
  "subject": "Mathematics",
  "subjectDisplay": "Joyful-Mathematics (English)",
  "bookCode": "bejm1",
  "subSubject": null,
  "chapterNum": 6,
  "title": "Decoration for",
  "language": "english",
  "sections": [
    {
      "heading": "Decoration for",
      "content": "Decoration for Celebration!\nRohan and his friends need garlands to decorate\ntheir homes for celebration. Each has 10 flowers .\nComplete the given table with the help of the above picture.\nDecoration for\nFestival\nZoha\nSimran\nRohan Akash \nSuwali\nJaved\nRohan 1 2\n10 + 2 = 12\n30 + 7 = 37\n40 + 8 = 48\n50 + 3 = 53\nSimran\nAkash\nSuwali\nJaved\nZoha\nName \nNumber of Number of Total number of\nReprint 2026-27\nHow many flowers are used by Rohan and Suwali\ntogether?\nI have\n10 + 2 = 12\nflowers.\nI have\n50 + 3 = 53\nflowers.\nRohan brings\nSuwali brings\nSuwali and Rohan\ntogether bring\n1 2\n5 3\n6 5\n10 + 2 = 12\n50 + 3 = 53\n60 + 5 = 65\n1 2\n+ 5 3\n1 2\n+ 5 3\n1 2\n+ 5 3\n6 5\nWow! We both\nhave 65 flowers.\nTens (T) Ones (O) T O T O\nReprint 2026-27\nZoha brings\nJaved brings\nZoha and Javed\ntogether bring\n2 0\n4 3\n6 3\n20 + 0 = 20\n40 + 3 = 43\n60 + 3 = 63\nZoha brings\nAkash brings\nZoha and Akash\ntogether bring\n2 0 20 + 0 = 20\n4 3\n+ 2 0\n4 3\n+ 2 0\n4 3\n+ 2 0\nWhat is the total number of flowers used by Zoha and\nAkash?\n4 8\n+ 2 0",
      "type": "text"
    },
    {
      "heading": "T OT O T O",
      "content": "T O\nHow many flowers are used by Zoha and Javed in all?\nReprint 2026-27\nLet us do it on Ginladi!\nWhat is the total number of flowers used by Rohan and\nSimran?\nRohan brings\nSimran brings\nRohan and Simran\ntogether bring\nA. 25 + 12 =\nB. 57 + 34 =\nLet us understand this way.\n57 + 34 = 57 + 30 + 4\n87 + 4 = 91\nCount ____ ahead of ____\nC. 24 + 43 =\nWe can write 24 + 40 + 3 = 64 + 3 = 67\n10 10 10 10\n24 34 44 54 64 67\n1 1 1\n25 37\n1111 111 111 11\n10 10 10\n57 67 77 87 91\n1 1 1 1\nCount 12 ahead\nof 25.\nReprint 2026-27\nA. 23 + 14 =\nNow add numbers on the\nnumber line.\nB. 24 + 16 =\nC. 11 + 22 =\nIt is difficult to count the\nbeads of ginladi every time.\nLet me write the numbers in\nplace of beads.\nI am calling this\na number line.\n0 1 2 3 4 5 6 7 8 9 10 11 12 13 14 15 16 17 18 19 20 21 22 23 24 25 26 27 28 29 30 31 32 33 34 35 36 37 38 39 40\n+10 +4\n0 1 2 3 4 5 6 7 8 9 10 11 12 13 14 15 16 17 18 19 20 21 22 23 24 25 26 27 28 29 30 31 32 33 34 35 36 37 38 39 40\n0 1 2 3 4 5 6 7 8 9 10 11 12 13 14 15 16 17 18 19 20 21 22 23 24 25 26 27 28 29 30 31 32 33 34 35 36 37 38 39 40\n1 2 3 4 5 6 7 8 9 10 11 12 13 14 15 16 17 18 19 20 21 22 23 24 25 26 27 28 29 30 31 32 33 34 35 36 37 38 39 40\nWe can get the number 43 in another way: 20 + 20 + 3\nRead the number line and fill the boxes.\n0 1 2 3 4 5 6 7 8 9 10 11 12 13 14 15 16 17 18 19 20 21 22 23 24 25 26 27 28 29 30 31 32 33 34 35 36 37 38 39 40\n+10 +6\nA. 22 + = 38\n0 1 2 3 4 5 6 7 8 9 10 11 12 13 14 15 16 17 18 19 20 21 22 23 24 25 26 27 28 29 30 31 32 33 34 35 36 37 38 39 40\n+10 +3\nB. 18 + =\nReprint 2026-27\nPlaying with Blocks\nMahi has some blocks. Isha came with her blocks to play. Let\nus help them in finding how many blocks they have in total.\n2 tens 3 ones\nMahi’s Blocks Isha’s Blocks\nand\n3 tens 8 ones\n5 tens 11 ones (1 tens 1 ones)\n6 tens 1 ones\nAdd these Numbers\nC. + =\n0 1 2 3 4 5 6 7 8 9 10 11 12 13 14 15 16 17 18 19 20 21 22 23 24 25 26 27 28 29 30 31 32 33 34 35 36 37 38 39 40\n+10 +10 +3\n4 4\n+ 2 3\n5 6\n+ 2 3\n6 0\n+ 2 5\n5 2\n+ 3 0\n+\nReprint 2026-27\nLet us find the total number of blocks.\n80 + 3 = 83\n+\n3 tens\n6 ones\n4 tens\n7 ones\n7 tens 13 ones\n+\n4 tens\n5 ones\n4 tens\n9 ones\n+\n3 tens\n2 ones\n5 tens\n8 ones\n+\n8 tens 1 ten\n4 ones\n+\n2 tens\n6 ones\n4 tens\n8 ones\n8 tens and 3 ones\nReprint 2026-27\nA. Rahim made 43 runs in one match and 58\nruns in another match. How many runs he made in the\ntwo matches together?\nIsha, do you\nknow, we can add without\ncounting all the blocks again\nand again?\nOh really, Mahi!\nCan you show\nme how?\nLet us Do\nT O\n3 6\n+ 4 7\nT O\n3 6\n+ 4 7\nT O\n3 6\n+ 4 7\n8 3\n(6 + 7 = 13) (3 + 4 + 1 = 8)\n1 1\nAdd\n+ 39\n+ 19\n+ 8 \n+ 58\n+ 35\nAdding ones\n1 tens and\n3 ones\nAdding tens\n8 tens\nShifting the tens\nReprint 2026-27\nB. Simarpreet had 12 colour pencils . Her\nmother gifted her 36 more colour pencils. How many\ntotal colour pencils does she have now?\nC. Heena collected 34 red marbles and 57 blue marbles\n. How many total marbles does she have now?\nD. Sarika spent `56 in the fair, while Manish spent\n`35 in the fair. What is the total money they both spent\nin the fair?\nE. There are 36 men and 47 women in the bus\n. How many people are there in the bus?\nLet us Count\nDiyas\nI made\n75 diyas in a day and\nsold 35 out of them.\nLet me count how\nmany diyas are left\nnow? 1, 2, 3...\nReprint 2026-27\nThat means if we take away\n35 from 75, then the answer\nwill be 40.\n75 – 35 = 40\nI have another way of\ndoing it. We can draw\nas many lines as the\nnumber of diyas left.\nInteresting!\nIs there any\nother way to find\nout?\nYes, we can\ndo this on\nginladi too.\nI count 75\nfirst and then I\nwill go 35 steps\nbackward.\nIf we have 32 diyas\nin the morning and\n12 diyas are sold\nby the evening.\nHow many diyas\nare left?\nOn taking away 12 from 32, we\nget 20.\n32 − 12 = 20\n20 32\n40 75\nReprint 2026-27\n9 18\nWe can also use the ginladi to find the answers of the\nfollowing.\n18 − 9 =Take away 9 from 18\n12 − 8 =Take away 8 from 12\n30 − 18 =Take away 18 from 30\n23 − 14 =Take away 14 from 23\n26 − 17 =Take away 17 from 26\nA.\nB.\nC.\nD.\nE.\nReprint 2026-27\n1 2 3 4 5 6 7 8 9 10 11 12 13 14 15 16 17 18 19 20\n11 111 11 111 111 11\nYesterday,\nwe counted left\nout diyas on the\nginladi.\nTell me how you did\nit? But, I don’t have a\nginladi at my home.\nIf I want to take away\n15 from 19, I count till\n19 first, then move 15\nsteps backward.\nLet us make a\nginladi on the\npaper then.\n19 − 15 = 4\nI have another\nway of doing\nsubtraction on\nthe number\nline.\nWe can directly\njump back 10 steps\nand then go 5 steps\nback to reach 4.\n1 2 3 4 5 6 7 8 9 10 11 12 13 14 15 16 17 18 19 20\n111 11 \nReprint 2026-27\nLet us do some practice on number line.\nRead the number line and fill the boxes.\n1 2 3 4 5 6 7 8 9 10 11 12 13 14 15 16 17 18 19 20 21 22 23 24 25 26 27 28 29 30\nA. 26 − =\n1 2 3 4 5 6 7 8 9 10 11 12 13 14 15 16 17 18 19 20 21 22 23 24 25 26 27 28 29 30 31 32 33 34 35 36 37 38 39 40\nB. 39 − 28 =\n1 2 3 4 5 6 7 8 9 10 11 12 13 14 15 16 17 18 19 20 21 22 23 24 25 26 27 28 29 30 31 32 33 34 35 36 37 38 39 40\nC. − =\n1 2 3 4 5 6 7 8 9 10 11 12 13 14 15 16 17 18 19 20 21 22 23 24 25 26 27 28 29 30 31 32 33 34 35 36 37 38 39 40\n1 10\nD. 38 − 11 =\n1 2 3 4 5 6 7 8 9 10 11 12 13 14 15 16 17 18 19 20 21 22 23 24 25 26 27 28 29 30\nE. 22 − 22 =\n1 2 3 4 5 6 7 8 9 10 11 12 13 14 15 16 17 18 19 20 21 22 23 24 25 26 27 28 29 30\nF. 14 − 0 =\n1 2 3 4 5 6 7 8 9 10 11 12 13 14 15 16 17 18 19 20 21 22 23 24 25 26 27 28 29 30 31 32 33 34 35 36 37 38 39 40\nG. 35 − 12 =\nDiscuss with children about subtracting zero and subtracting\nthe number with itself by taking examples from daily\nlife situations, like, spending all money or spending no\nmoney.\nReprint 2026-27\nPlaying with Blocks\n10 1\nI have 45 I give 12\nto my friend. I am left with\nA. Shikha has `82. She bought pencils for `22. How much\nmoney is she left with?\nB. Ruby has `60. She bought a notebook for `20. How much\nmoney is she left with?\nT O\n4 5\n− 1 2\nT O\n4 5\n− 1 2\nT O\n4 5\n− 1 2\n3 3\n2 4\n– 1 3\n5 4\n– 3 1\n3 2\n– 1 2 \n4 6\n– 3 4\nSubtract 24 from 37\n3 tens 7 ones 2 tens 4 ones\nT O\n3 7\n− 2 4\nLet us Do\nReprint 2026-27\nJyoti, can I have 1\nand 8 ?\nI have only 6 loose\n. I think I should\nopen a .\nNow I can\ngive 8 to\nmummy.\nDecorating with Garlands\nReprint 2026-27\nTo give 18\n4 6\n− 1 8\n(opens 1 = 16 )\n16 − 8 = 8\n4 6\n− 1 8\n2 8\n4 6\n− 1 8\n3 16T O \nT O\nT O\nI am left with\n2 garlands and 8\nflowers or 28 flowers\nin all.\nNow, Jyoti has 28 flowers in all. She gives 5 to her\nfriend. Help Jyoti to find out how many flowers is she\nleft with?\n2 8\n− 5\nReprint 2026-27\nNow, Jyoti has 54 flowers in all. She gives 28 to her mother.\nHow many flowers is she left with?\nJyoti has 73 flowers in all. She gives 47 to her mother. How\nmany flowers is she left with?\nI am left with 2\ngarlands and 6 flowers or\n26 flowers in all.\nGarlands Flowers\nJyoti has 7\n7Jyoti gives\nJyoti is\nleft with\n5 4\n− 2 8\n5 4\n− 2 8\n5 4\n− 2 8\n2 6\n14 − 8 = 6\nOh! I need to\nopen one garland. Then\nI will have 4 garlands and\n14 flowers, from it I can\ngive 8 flowers.\nReprint 2026-27\nLet us Do\n− 18\n− 37\n− 45\n− 27\n− 48\nSkip the Rope\nAman and Avni are\nplaying ‛skip the\nrope’. Both have\nto complete 20\nskips. A skip can be\ncounted when the\nrope passes under\nthe feet. They will get\ntwo chances to skip.\nIf one misses any\nskip in the first time\nthen they will get\none more chance to\ncomplete 20 skips.\nA. Aman skipped 14 times in the first chance. How many\nmore skips he has to make to complete 20 skips?\nB. Avni skipped 12 times in the first chance. How many\nmore skips she has to make to complete 20 skips?\n20 − 14 = ____\n20 − 12 = ____\n14 + ____ = 20\n12 + ____ = 20\nReprint 2026-27\nLet us Do\nA. Anushka collected 63 shells . She gave 26\nshells to her brother. How many shells are left with\nher?\nB. 54 passengers were sitting in the bus and 16\ngot down at the bus stand. How many are there in the\nbus now?\nC. There were 40 balloons and 13 balloons got\nburst. How many balloons are left?\nD. Kanika made 72 bangles . She sold 36 bangles.\nHow many bangles are left with Kanika now?\nE. 56 birds were sitting on the tree . A few more\nbirds joined them. Now there are 87 birds. Find out the\nnumber of birds that came later.\nF. Arman dribbled the ball 18 times. How many more\ntimes should he dribble the ball to complete 35 taps?\nWe can use any of the method—\nginladi, number strip, number block or\nmoti mala to find the answers.\nReprint 2026-27\nAddition and Subtraction Facts\nFill the missing numbers to complete the fact family.\n20 30\n20 + 30 = ____\n30 + ____ = 50\n50 − ____ = 20\n____ − 20 = 30\n20, 30, 50\n80 20\n20, 80, 100\n10 20\n10 + 20 = ____\n___ + ___ = ___\n30 − ____ = 10\n30 − ____ = 20\n10, 20, 30\nAddition and Subtraction Pyramid\n5 3\n6 8\n6 4\n3 8\nAddition pyramid\nSubtraction pyramid\n4 3\nReprint 2026-27\nNow complete the following diagrams.\nA. B.\nHania and Mansi’s Gift\nHania and Mansi want to give a gift to their mother. For\nits decoration, they purchased some ribbons and a gift\nwrapper.\nThere are `78 in the purse. The cost of a gift wrapper is `24\nand the cost of ribbons is `37.\nA. How much money did they spend?\nB. How much money is left with them?\nHere, 3 + 9 = 12 9 + 6 = 15\n6 + 5 = 11 5 + 3 = 8\nProject Work\nDaljeet has solved some questions and writen down their answers.\nWhat do you think? Are they correct? Verify the answers.\nCorrect it if you find them wrong.\n+ 36\n+ 58\n− 17\n− 78\n− 17\nLook at this diagram.\n10 9\nReprint 2026-27",
      "type": "procedure"
    }
  ],
  "learningObjectives": [
    "Understand the key concepts of Decoration for",
    "Identify and explain the main ideas covered in this chapter",
    "Apply knowledge from this chapter to real-world situations",
    "Recall important terms and definitions from Decoration for"
  ],
  "wordCount": 2627,
  "pdfUrl": "https://ncert.nic.in/textbook/pdf/bejm106.pdf",
  "extractedAt": "2026-05-20T22:21:44.052Z"
}