{
  "class": 5,
  "subject": "EVS",
  "subjectDisplay": "Looking Arround",
  "bookCode": "eeap1",
  "subSubject": null,
  "chapterNum": 1,
  "title": "Super Senses",
  "language": "english",
  "sections": [
    {
      "heading": "Super Senses",
      "content": "Super Senses 11111\nAs you walked softly past a\nsleeping dog, its ears shot up\nat once.\nYou were eating in the\nplayground, an eagle flew\ndown and took away your\nroti.\nHas this ever\nhappened to you?\n1. Super Senses\nYou dropped something sweet on\nthe ground and within minutes\nmany ants collected around it.\nAnimals also have different senses. They can see, hear,\ntaste, smell and feel. Some animals can see their prey from\nfar away. Some can hear even the faintest sound. Some\nanimals can find their friends by their smell. The animal\nworld is full of examples of amazing senses!\nWhy does it\nhappen? Think\nand tell\n2024-25\n2 Looking Around\nHow did the ant recognise a friend?\nAn ant was going along on the ground. It saw a group\nof ants coming from the other side. The first ant quickly\ncame back to its hole. The ant guarding the hole\nrecognised it and let it in.\nThink and Tell\nw How did the ant know that the other ants\nwere not from its group?\nw How did the guard ant recognise this ant?\nTry this and write\nDrop some sugar, jaggery or anything sweet on the ground.\nWait until the ants come there.\nw How long did it take for the ants to come?\nw Did one ant come first or a group of ants came together?\nw What did the ants do with the food?\nw Where do they go from there?\nw Do they move in a line?\nTeacher’s Note : Children of this age are interested in animals. Encourage them\nto share their experiences. Children should be supported to carry out observation\nactivities which require patience.\n2024-25\nSuper Senses 3\nw Now can you guess why the ants behaved\nlike that when you blocked their path?\nSome male insects can recognise their\nfemales by their smell.\nw Have you ever been troubled by mosquitoes?\nJust think, how do they know where\nyou are?\nMosquitoes can find you by the smell of your\nbody. They also find you by the smell of the\nsole of your feet and the heat of your body.\nI am a silk worm. I\ncan find my female\nworm from many\nkilometres away by\nher smell.\nMany years ago a scientist did many experiments like this.\nHe found out that as the ants move, they leave a smell on the\nground. The other ants follow the smell to find the way.\nNow carefully, without harming the ants, block their path\nfor a while with a pencil.\nw Now observe, how do the ants move?\nw Have you seen a dog sniffing here\nand there? What do you think it is\ntrying to smell?\nDogs mark out their own area on\nthe road. They can make out if another\ndog has come into their area by the\nsmell of its urine or potty (latrine).\n2024-25\n4 Looking Around\nw Do you and your friends have similar answers?\nWrite\nw In what ways do human beings make use of this special\nsense of smell of dogs?\nw When do you find your sense of smell helpful to you? List\nsome examples. Like – to know by its smell that food has\ngone bad or that something is burning.\nw Name the animals that you would be able to recognise only\nby their smell, without seeing them?\nw Write the names of five things whose smell you like and five\nthings whose smell you do not like.\nI like the smell of I do not like the smell of\n&&&&&&&&&&&&&&&&&&&\n&&&&&&&&&&&&&&&&&&&\n&&&&&&&&&&&&&&&&&&&\n&&&&&&&&&&&&&&&&&&&\n&&&&&&&&&&&&&&&&&&&\n&&&&&&&&&&&&&&&&&&&&\n&&&&&&&&&&&&&&&&&&&&\n&&&&&&&&&&&&&&&&&&&&\n&&&&&&&&&&&&&&&&&&&&\n&&&&&&&&&&&&&&&&&&&&\n2024-25\nSuper Senses 5\nTeacher’s Note : Sushila’s example illustrates a common situation in families.\nDiscuss with children how we often find a smell ‘bad’ when we think it is\nfrom something dirty. If we analyse it, we may not be so offended by certain\nsmells.\nWhy so?\nToday Rajni had to go out for some\nimportant work. She had to leave her six-\nmonth old son Deepak with her sister\nSushila. Sushila also has a baby of\nthe same age. It was funny that both\nthe babies did potty at the same\ntime. She happily cleaned her\ndaughter but when she was cleaning\nher sister’s son Deepak, she covered\nher nose with her dupatta (scarf).\nDiscuss\nw Do the clothes of any of your family members smell?\nwhose?\nw Did you ever come across any smell in a crowded place\nsuch as a fair, bus, train etc.\nThink and discuss\nw Sushila covered her nose when she cleaned Deepak’s\nnappy, but not when she cleaned her daughter. Why do\nyou think she did this?\nw How do you feel when you walk near a heap of garbage?\nThink of the children who spend the whole day picking\nthings from such garbage.\nw Is a smell ‘good’ or ‘bad’ for everyone in the same way?\nOr does it depend on how each one feels about it?\n2024-25\n6 Looking Around\nTeacher’s Note : When a bird focuses both eyes on an object, it can estimate the\ndistance. When its eyes focus on two different things, it increases its range of\nvision. Children will understand this better, once they start observing the location\nof eyes of different birds. While seeing with one eye and then with two eyes, children\nwill understand how with two eyes, the span of vision increases.\nLet’s see\nw Write the name of a bird which has eyes in front of its head\n(like in humans).\nw Write the names of some birds which have eyes on either\nside of the head. What is the size of their eyes as compared\nto the size of their head?\nMost of the birds have their eyes on either side of the head.\nTheir eyes can focus on two different things at a time. When they\nlook straight ahead, both their eyes focus on the same object.\nYou must have seen birds moving their neck very often. Do\nyou know why? In most of the birds, eyes are fixed and cannot\nmove. So birds have to turn their heads to see around.\nLooking with one or both eyes\nClose your right eye or cover it with your hand. Tell your\nfriend to stand to your right, at some distance, and ask him\nto do some action (wave hand, shake head, etc.)\nw Could you see your friend’s action, without moving your neck?\nw Now try to look at your friend’s action with both your eyes\nopen but without moving your neck.\nw What was the difference on looking with one or both eyes?\n2024-25\nSuper Senses 7\nDo animals see colours?\nAnimals cannot see as many colours as we can. See how\nthings in these pictures will be seen by some animals.\nDeepa Balsawar\nIt is believed that animals that are awake in\nthe daytime can see some colours. Those animals\nthat are awake at night can see things only in\nblack and white colours.\nw Now toss a small ball or a coin and try to catch it. Try\nthis with both your eyes open. Then close one eye and\ntry to catch it. When was it easier to catch?\nw Imagine how it would be to have your eyes in place of\nyour ears? What would you be able to do then, which\nyou cannot do now?\nSome birds like kites, eagles, vultures can see four times\nas far as we can. These birds can see things from a distance\nof eight metres what we can see from a distance of two metres.\nw Now can you guess from what distance can an eagle in the\nsky can see a roti on the ground?\n2024-25\n8 Looking Around\nTry this\nFor this activity find a quiet place in your school.\nTell one of your friends to stand at a short\ndistance and ask him to say something softly.\nThe rest of you should listen carefully. Then all\nof you put your hands behind your ears, as\nshown in the picture. Let the same child say\nsomething again as softly as before. In which\ncase was the sound sharper? Ask your friends\ntoo.\nw Put your hands over your ears and say\nsomething. Can you hear your own voice?\nSharp ear\nIn Class IV, you read that we cannot easily see birds’ ears. Their ears\nare small holes covered with feathers.\nWrite\nw The names of ten animals whose ears can\nbe seen.\nw The names of some animals whose\nears are bigger than our ears.\nThink\nw Is there some link between the size of\nanimals’ ears and their hearing?\n2024-25\nSuper Senses 9\nSounds send messages\nw High up on a tree, a langur warns others of\ndangers like a tiger or leopard. The langur\ndoes this by making a special warning call.\nw Birds also give alarm calls to warn about\nthe danger. Some birds even have different\nsounds for different kinds of dangers. For\nexample, there is a different warning call\nif the enemy is coming from the sky or if\nthe enemy is on the ground.\nw Fishes give alarm call by electric signals.\nw Sit near a desk. Tap the desk once with\nyour hand. Listen carefully. Now put your\near on the desk as shown in the picture.\nTap on the desk once again with your hand.\nListen again. Was there any difference in\nthe sound of the tap?\nSome animals start behaving in a different way when an\nearthquake or storm is about to come. People who live in\nforests and can observe such behaviour of animals come to\nknow of the danger.\nIn December 2004, few tribes that live in the forests of\nthe Andaman Islands noticed the animals behaving in a\ndifferent manner. They guessed some danger. So they\nmoved away to a safer part of the island. Soon after, the\nislands were hit by the tsunami but these people were\nsaved.\nDeepa Balsawar\nThis is how snakes hear. They do not have external ears\n(which you can see). They only feel the vibrations on the ground.\n2024-25\n10 Looking Around\nDolphins also make different\nsounds to give messages to\neach other. Scientists believe\nthat many animals have a\nspecial language of their own.\nTeacher’s Note : The lesson gives examples of several animals with ‘sensitive’\nsenses. Encourage children to find out more such animal senses from newspapers,\nTV programmes, etc.\nWrite\nw Can you understand the sounds of some animals?\nWhich animals?\nw Do some animals understand your language?\nWhich ones?\nSay it with sounds\nJust like birds and dolphins you can also make your own\nlanguage of sounds for giving messages. Remember you have\nto talk to your friends with only sounds and no words. How\nand when will you need to give an alarm call? For example,\nwhen the teacher is coming to the classroom!\nSleeping-waking\nSome animals go into a long, deep sleep in certain seasons.\nThen they are not seen for many months.\nw Have you noticed that during the cold season you cannot\nsee any lizard in the house? Where do you think they\nhave gone?\n2024-25\nSuper Senses 11\nSloth\nIt looks like a bear but is not. It is a sloth. It\nspends almost 17 hours a day sleeping while\nhanging upside down on a tree branch. The sloth\neats the leaves of the same tree on which it lives.\nIt hardly needs anything else. When it has eaten\nenough leaves from that tree, it moves to the\nnearby tree.\nSloths live for about 40 years and in that time\nthey move around only eight trees. Once a week\nit comes down from the tree to relieve itself.\nIf you were to show a sloth’s daily routine\n(sleeping and waking) in a 24-hour clock, this\nis what the clock would look like.\nGiven here is the sleeping time of some animals. Write below each\npicture for how many hours a day that animal sleeps.\nHow will you show the clock\nfor a house-lizard in winters?\nTeacher’s Note : The sleeping and waking routine of animals is given in a 24 hour\nclock to encourage children to think about fractions (one-third, one-fourth, etc.)\nExplain phrases like ‘call of nature’, ‘relieve itself ’ etc.\nw When you see different animals, do you have any questions about\nthem? Make a list of ten such questions.\n6 Hours18 Hours\n24 Hours\n12 Hours\n24 Hours\n6 Hours\n12 Hours\n18 Hours\nTime for which\nsloth is awake\nCow__________ Python__________ Giraffe__________ Cat__________\nSleeping time for sloth\n2024-25\n12 Looking Around\nEach tiger has its own area\nwhich may cover several\nkilometres. T igers mark\ntheir area with their urine.\nA tiger can at once come\nto know if there is another\ntiger in its area by the\nsmell of the urine. A tiger\nwill avoid going into\nanother tiger’s area.\nA tiger’s sense of hearing\nis so sharp that it can\nmake out the difference\nbetween the rustling of\nleaves and the sound of\nan animal moving on the\ngrass. The ears of the tiger\ncan move in different\ndirections and this helps\nto catch the sounds from\nall around.\nT igers make dif fer ent\nsounds for different\npurposes like when it is\nangry or to call out to a\ntigress. It can also roar or\nsnarl. It’s roar can be\nheard upto 3 kilometres\naway.\nA tiger can see six\ntimes better at\nnight than most of\nus.\nThe tiger’s whiskers\nare very sensitive\nand can sense the\nmovements or\nvibrations in air.\nThey help the tiger\nmove in the dark\nand find its prey.\n2024-25\nSuper Senses 13\nThe tiger is one of the most alert animals. And yet, today\ntigers are in danger.\nw What do you think are some of the dangers to tigers in\nthe jungle?\nw Can human beings also be a threat to animals? How?\nDo you know that today many animals are killed and their\nparts are sold? Elephants are killed for their tusks, rhinoceros\nfor its horn, tigers, crocodiles and snakes for their skins.\nMusk deer are killed just to make a little scent from its musk.\nPeople who kill animals are called hunters and poachers.\nThe number of tigers and many other animals in our country is reducing.\nThere is a danger that some of them will soon disappear. To protect the\nanimals, our government has made some forests as protected areas. Some\nof them are the Jim Corbett National Park in Uttrakhand and ‘Ghana’ in\nBharatpur district of Rajasthan. In these areas nobody can hunt animals\nor destroy the jungle.\nTeacher’s Note : Discuss with children the various threats to the tiger – poaching,\ndestruction of forests for roads, dams, human settlements, forest fires, etc.\nWhat we have learnt\nw Have you noticed that sometimes singers put\ntheir hand on their ear when they sing?\nWhy do you think they may be doing this?\nw Give examples of animals that may have a very strong\nsense of sight, hearing or smell.\nFind out\nw Where are other such National Parks in India?\nw Collect information on these and write a report.\n2024-25\n14 Looking Around\na\nb\nc\nd\nLet’s make a paper dog\nFor this you need: thick paper, pencil, scissors,\nsketch pen.\nw Cut a long strip of thick paper. Mark the strip as\nshown here.\nw Make small cuts on the lines marked 1 to 6.\nw Hook together the cuts on the number 1 and 2 (see\npicture a).\nw In the same way, hook together 3 in 4, and 5 in 6 (see\npicture b and c)\nw Make a cut in the mark on the leg (see picture c).\nw Turn down the corners of the strip on top of the head,\nto make the ears (picture d)\nw Mark the eyes and nose with a sketch pen.\nWasn’t that fun!\nBow, Wow!\nGive your dog\na name!\nPaper Strip\n2024-25",
      "type": "text"
    }
  ],
  "learningObjectives": [
    "Understand the key concepts of Super Senses",
    "Identify and explain the main ideas covered in this chapter",
    "Apply knowledge from this chapter to real-world situations",
    "Recall important terms and definitions from Super Senses"
  ],
  "wordCount": 2681,
  "pdfUrl": "https://ncert.nic.in/textbook/pdf/eeap101.pdf",
  "extractedAt": "2026-05-20T22:23:03.272Z"
}